prisma_cloud_pipeline/__init__.py
prisma_cloud_pipeline/__main__.py
prisma_cloud_pipeline/lib.py
prisma_cloud_pipeline/rules-schema.json
prisma_cloud_pipeline-0.1.5.dist-info/entry_points.txt
prisma_cloud_pipeline-0.1.5.dist-info/WHEEL
prisma_cloud_pipeline-0.1.5.dist-info/METADATA
prisma_cloud_pipeline-0.1.5.dist-info/RECORD
