Metadata-Version: 2.1
Name: prisma-cloud-pipeline
Version: 0.1.5
Summary: Export Prisma Cloud container findings to a CI pipeline, and identify un-triaged findings
Home-page: https://github.com/thalescpl-io/prisma-cloud-pipeline
License: MIT
Keywords: static-analysis,twistlock,devsecops,prisma-cloud
Author: Michael Macnair
Author-email: michael.macnair@thalesgroup.com
Requires-Python: >=3.8,<4.0
Classifier: License :: OSI Approved :: MIT License
Classifier: Programming Language :: Python :: 3
Classifier: Programming Language :: Python :: 3.10
Classifier: Programming Language :: Python :: 3.8
Classifier: Programming Language :: Python :: 3.9
Requires-Dist: jq (>=1.1,<1.3)
Requires-Dist: jsonschema (>=3.2,<4.4)
Requires-Dist: pyyaml (>=5.3,<6.1)
Requires-Dist: requests (>=2.25,<2.27)
Requires-Dist: tabulate (>=0.8,<0.9)
Requires-Dist: types-PyYAML (>=5.4.10,<6.0.0)
Requires-Dist: types-requests (>=2.25.9,<3.0.0)
Requires-Dist: types-tabulate (>=0.8.2,<0.9.0)
Project-URL: Repository, https://github.com/thalescpl-io/prisma-cloud-pipeline
